{
  "schema": "fap.report.cards.v1",
  "engine": "v1.2",
  "section": "growth",
  "meta": {
    "package": "MBTI-CN-v0.2.2",
    "updated_at": "2025-12-21",
    "change_id": "LAUNCH-V1-REPORT-CARDS-GROWTH",
    "notes": "Launch v1.0: growth cards production pool (23). 10 axis directional strong-only (min_delta=12) + 6 axis intro guardrail-friendly (min_delta=0, AT split A/T) + 7 core fallback-safe. Tags are primary selector hooks; match rules are optional constraints."
  },
  "rules": {
    "min_cards": 2,
    "target_cards": 3,
    "max_cards": 6,
    "fallback_tags": [
      "kind:core"
    ],
    "sort": [
      "priority_desc"
    ]
  },
  "items": [
    {
      "id": "growth_axis_EI_E_strong",
      "section": "growth",
      "title": "E 偏好较强：成长来自“碰撞与复盘”",
      "desc": "你更容易在交流、协作与现场推进中升级自己：先动起来，再迭代。",
      "bullets": [
        "在反馈中快速校准",
        "边做边学效率更高",
        "在团队中更容易被激发"
      ],
      "tips": [
        "给每次讨论留 3 分钟：写下结论与下一步",
        "别把成长等同于社交：要有输出与复盘"
      ],
      "tags": [
        "kind:axis",
        "axis:EI:E",
        "state:strong",
        "topic:feedback"
      ],
      "priority": 96,
      "match": {
        "axis": {
          "dim": "EI",
          "side": "E",
          "min_delta": 12
        }
      },
      "access_level": "paid",
      "module_code": "core_full"
    },
    {
      "id": "growth_axis_EI_I_strong",
      "section": "growth",
      "title": "I 偏好较强：成长来自“深度与沉淀”",
      "desc": "你更容易靠深度思考与持续沉淀拉开差距：安静时，你更强。",
      "bullets": [
        "独立学习效率更高",
        "擅长把复杂问题想透",
        "更需要低打扰环境"
      ],
      "tips": [
        "设置固定深度时间块（如 2×45 分钟）",
        "把学习输出成笔记/卡片，沉淀会很快复利"
      ],
      "tags": [
        "kind:axis",
        "axis:EI:I",
        "state:strong",
        "topic:deepwork"
      ],
      "priority": 96,
      "match": {
        "axis": {
          "dim": "EI",
          "side": "I",
          "min_delta": 12
        }
      },
      "access_level": "paid",
      "module_code": "core_full"
    },
    {
      "id": "growth_axis_SN_S_strong",
      "section": "growth",
      "title": "S 偏好较强：用“方法与练习”稳步升级",
      "desc": "你更适合通过可重复练习与流程化方法成长：一步一步把能力做扎实。",
      "bullets": [
        "擅长用练习形成肌肉记忆",
        "对细节与标准更敏感",
        "更相信验证与经验"
      ],
      "tips": [
        "把技能拆成 checklist，每周练一个小模块",
        "每月做一次‘复盘表’，看哪些习惯最有效"
      ],
      "tags": [
        "kind:axis",
        "axis:SN:S",
        "state:strong",
        "topic:practice"
      ],
      "priority": 95,
      "match": {
        "axis": {
          "dim": "SN",
          "side": "S",
          "min_delta": 12
        }
      },
      "access_level": "paid",
      "module_code": "core_full"
    },
    {
      "id": "growth_axis_SN_N_strong",
      "section": "growth",
      "title": "N 偏好较强：用“框架与洞察”跨级成长",
      "desc": "你更适合通过搭框架、找规律、做抽象来成长：一通百通。",
      "bullets": [
        "善于从模式里找本质",
        "学习迁移能力强",
        "能快速提出新方向"
      ],
      "tips": [
        "把学习整理成 1 页框架图，理解会更稳",
        "每次灵感落地 3 条 next step，别停在想法里"
      ],
      "tags": [
        "kind:axis",
        "axis:SN:N",
        "state:strong",
        "topic:framework"
      ],
      "priority": 95,
      "match": {
        "axis": {
          "dim": "SN",
          "side": "N",
          "min_delta": 12
        }
      },
      "access_level": "paid",
      "module_code": "core_full"
    },
    {
      "id": "growth_axis_TF_T_strong",
      "section": "growth",
      "title": "T（理性）偏好较强：用“标准化复盘”升级决策力",
      "desc": "你更适合用指标、原则与复盘机制成长：把判断变成可训练的能力。",
      "bullets": [
        "擅长用规则校准行为",
        "愿意面对问题本身",
        "能扛住压力做取舍"
      ],
      "tips": [
        "建立‘决策复盘’：当时依据/结果/下次改进",
        "表达时先给结论再给理由，协作会更省力"
      ],
      "tags": [
        "kind:axis",
        "axis:TF:T",
        "state:strong",
        "topic:decision"
      ],
      "priority": 94,
      "match": {
        "axis": {
          "dim": "TF",
          "side": "T",
          "min_delta": 12
        }
      },
      "access_level": "paid",
      "module_code": "core_full"
    },
    {
      "id": "growth_axis_TF_F_strong",
      "section": "growth",
      "title": "F（感受）偏好较强：用“关系与边界”让成长更稳",
      "desc": "你更适合在关系与价值中成长：学会表达需求、设定边界，你会更强。",
      "bullets": [
        "共情与连接是你的资源",
        "更在意意义与价值一致",
        "擅长照顾团队氛围"
      ],
      "tips": [
        "把‘不好意思’换成‘我需要…/我能…’",
        "为自己设一条边界线：什么情况必须拒绝"
      ],
      "tags": [
        "kind:axis",
        "axis:TF:F",
        "state:strong",
        "topic:boundary"
      ],
      "priority": 94,
      "match": {
        "axis": {
          "dim": "TF",
          "side": "F",
          "min_delta": 12
        }
      },
      "access_level": "paid",
      "module_code": "core_full"
    },
    {
      "id": "growth_axis_JP_J_strong",
      "section": "growth",
      "title": "J 偏好较强：用“计划与闭环”持续进阶",
      "desc": "你更适合用计划驱动成长：拆目标、定节奏、做复盘，升级很快。",
      "bullets": [
        "擅长把目标拆成里程碑",
        "对节点与进度敏感",
        "能把事情收尾做扎实"
      ],
      "tips": [
        "给计划留 15% 缓冲，避免太满导致挫败",
        "练习‘60 分交付线’，再迭代到 90 分"
      ],
      "tags": [
        "kind:axis",
        "axis:JP:J",
        "state:strong",
        "topic:plan"
      ],
      "priority": 94,
      "match": {
        "axis": {
          "dim": "JP",
          "side": "J",
          "min_delta": 12
        }
      },
      "access_level": "paid",
      "module_code": "core_full"
    },
    {
      "id": "growth_axis_JP_P_strong",
      "section": "growth",
      "title": "P 偏好较强：用“探索—收束”跑出成长速度",
      "desc": "你更适合通过探索与试错成长：先跑通，再优化，速度就是优势。",
      "bullets": [
        "学习路径更灵活",
        "试错迭代快",
        "在变化中抓机会"
      ],
      "tips": [
        "给探索设置收束点：到点必须定一个版本",
        "用看板把任务可视化，避免发散"
      ],
      "tags": [
        "kind:axis",
        "axis:JP:P",
        "state:strong",
        "topic:explore"
      ],
      "priority": 94,
      "match": {
        "axis": {
          "dim": "JP",
          "side": "P",
          "min_delta": 12
        }
      },
      "access_level": "paid",
      "module_code": "core_full"
    },
    {
      "id": "growth_axis_AT_A_strong",
      "section": "growth",
      "title": "A（自信型）偏好较强：用“大胆推进+反证”更强",
      "desc": "你更能在压力下保持笃定。成长关键是：大胆推进的同时加一道反证。",
      "bullets": [
        "推进快、内耗少",
        "敢承担关键决策",
        "能稳住节奏"
      ],
      "tips": [
        "每次重大判断加 1 条反证：它为什么可能错？",
        "把‘确定’与‘假设’分开写清楚"
      ],
      "tags": [
        "kind:axis",
        "axis:AT:A",
        "state:strong",
        "topic:confidence"
      ],
      "priority": 92,
      "match": {
        "axis": {
          "dim": "AT",
          "side": "A",
          "min_delta": 12
        }
      },
      "access_level": "paid",
      "module_code": "core_full"
    },
    {
      "id": "growth_axis_AT_T_strong",
      "section": "growth",
      "title": "T（敏感型）偏好较强：用“完成线”终结过度打磨",
      "desc": "你更谨慎、校准更强。成长关键是：设完成线，别让完美主义拖慢你。",
      "bullets": [
        "风险意识强",
        "愿意自省与修正",
        "质量要求高"
      ],
      "tips": [
        "设一个完成线：到线就交付，再迭代",
        "把担心写成清单并排序，只先解决最重要的一条"
      ],
      "tags": [
        "kind:axis",
        "axis:AT:T",
        "state:strong",
        "topic:calibration"
      ],
      "priority": 92,
      "match": {
        "axis": {
          "dim": "AT",
          "side": "T",
          "min_delta": 12
        }
      },
      "access_level": "paid",
      "module_code": "core_full"
    },
    {
      "id": "growth_axis_EI_E_intro",
      "section": "growth",
      "title": "E 轻解释：成长更靠“互动反馈”",
      "desc": "即便不是强外向，你也会在适度交流中更快校准与前进。",
      "bullets": [
        "讨论能帮助你理清思路",
        "更愿意用协作推进",
        "反馈让你升级更快"
      ],
      "tips": [
        "用短讨论+行动项替代长拉扯",
        "每次交流结束写下 1 条改进点"
      ],
      "tags": [
        "kind:axis_intro",
        "axis:EI:E",
        "state:clear"
      ],
      "priority": 60,
      "match": {
        "axis": {
          "dim": "EI",
          "side": "E",
          "min_delta": 0
        }
      },
      "access_level": "paid",
      "module_code": "core_full"
    },
    {
      "id": "growth_axis_EI_I_intro",
      "section": "growth",
      "title": "I 轻解释：成长更靠“安静沉淀”",
      "desc": "即便不是强内向，你也会在独处与思考中更快恢复与校准。",
      "bullets": [
        "独处更能恢复专注",
        "更偏好深度学习",
        "更喜欢先想清楚再表达"
      ],
      "tips": [
        "把学习输出成卡片/笔记，复利会更明显",
        "给自己固定深度时段，别被碎片化吞掉"
      ],
      "tags": [
        "kind:axis_intro",
        "axis:EI:I",
        "state:clear"
      ],
      "priority": 60,
      "match": {
        "axis": {
          "dim": "EI",
          "side": "I",
          "min_delta": 0
        }
      },
      "access_level": "paid",
      "module_code": "core_full"
    },
    {
      "id": "growth_axis_JP_J_intro",
      "section": "growth",
      "title": "J 轻解释：成长更靠“计划与闭环”",
      "desc": "即便不算强 J，你也更舒服在有节奏、有复盘的推进方式里。",
      "bullets": [
        "更愿意先定关键节点",
        "更喜欢明确优先级",
        "收尾会让你更安心"
      ],
      "tips": [
        "计划做轻：只定 3 个关键节点",
        "每周一次复盘：保留/删除/新增"
      ],
      "tags": [
        "kind:axis_intro",
        "axis:JP:J",
        "state:clear"
      ],
      "priority": 58,
      "match": {
        "axis": {
          "dim": "JP",
          "side": "J",
          "min_delta": 0
        }
      },
      "access_level": "paid",
      "module_code": "core_full"
    },
    {
      "id": "growth_axis_JP_P_intro",
      "section": "growth",
      "title": "P 轻解释：成长更靠“探索与迭代”",
      "desc": "即便不算强 P，你也更舒服先尝试、再收束，用迭代找到最优路径。",
      "bullets": [
        "更愿意先试出可行性",
        "更能适应变化",
        "更喜欢保留选择空间"
      ],
      "tips": [
        "探索要有收束点：到点必须定一个版本",
        "把任务可视化，避免发散拖延"
      ],
      "tags": [
        "kind:axis_intro",
        "axis:JP:P",
        "state:clear"
      ],
      "priority": 58,
      "match": {
        "axis": {
          "dim": "JP",
          "side": "P",
          "min_delta": 0
        }
      },
      "access_level": "paid",
      "module_code": "core_full"
    },
    {
      "id": "growth_axis_AT_A_intro",
      "section": "growth",
      "title": "A（自信型）轻解释：稳住节奏、敢推进",
      "desc": "即便不是强 A，你也可能在关键时刻更愿意先定方向、再迭代。",
      "bullets": [
        "更敢推进决定",
        "波动更小、更少内耗",
        "能稳定节奏"
      ],
      "tips": [
        "重大判断加一次反证检查",
        "把‘确定’与‘假设’分开表达"
      ],
      "tags": [
        "kind:axis_intro",
        "axis:AT:A",
        "state:clear"
      ],
      "priority": 56,
      "match": {
        "axis": {
          "dim": "AT",
          "side": "A",
          "min_delta": 0
        }
      },
      "access_level": "paid",
      "module_code": "core_full"
    },
    {
      "id": "growth_axis_AT_T_intro",
      "section": "growth",
      "title": "T（敏感型）轻解释：认真校准、持续优化",
      "desc": "即便不是强 T，你也可能在压力下更倾向复查修正，让结果更可靠。",
      "bullets": [
        "风险嗅觉更强",
        "更愿意自省与修正",
        "更在意做对"
      ],
      "tips": [
        "设定完成线：到线就交付，再迭代",
        "把担心写成清单并排序，只先解决最重要的一条"
      ],
      "tags": [
        "kind:axis_intro",
        "axis:AT:T",
        "state:clear"
      ],
      "priority": 56,
      "match": {
        "axis": {
          "dim": "AT",
          "side": "T",
          "min_delta": 0
        }
      },
      "access_level": "paid",
      "module_code": "core_full"
    },
    {
      "id": "growth_core_01",
      "section": "growth",
      "title": "你的成长主线：把强项做成可复用资产",
      "desc": "成长最快的方法不是到处补短板，而是把强项沉淀成方法论与作品。",
      "bullets": [
        "把经验写成 SOP/清单",
        "把成果写成案例/作品集",
        "把思考写成框架/工具"
      ],
      "tips": [
        "每完成一个项目补一页复盘卡：做了什么/学到什么/下次怎么更好",
        "让输出可被复用，你会越做越轻松"
      ],
      "tags": [
        "kind:core",
        "tone:neutral",
        "topic:assets"
      ],
      "priority": 100,
      "access_level": "preview",
      "module_code": "core_full"
    },
    {
      "id": "growth_core_02",
      "section": "growth",
      "title": "升级方法：从“做事”到“定义问题”",
      "desc": "当你能定义问题、提出标准、设计路径，你的价值会跨级提升。",
      "bullets": [
        "从执行 → 负责模块",
        "从模块 → 搭系统",
        "从系统 → 负责结果"
      ],
      "tips": [
        "每次接任务先问 3 个问题：目标是什么？标准是什么？风险是什么？",
        "把方案写成 1 页纸：目标-路径-指标-风险"
      ],
      "tags": [
        "kind:core",
        "tone:neutral",
        "topic:levelup"
      ],
      "priority": 97,
      "access_level": "preview",
      "module_code": "core_full"
    },
    {
      "id": "growth_core_03",
      "section": "growth",
      "title": "自我管理：用节奏感替代硬拼",
      "desc": "你更适合用节奏驱动：推进—休整—复盘—再推进，稳定输出才是护城河。",
      "bullets": [
        "有节奏时更高效",
        "复盘能快速升级",
        "过度消耗会明显降质"
      ],
      "tips": [
        "给自己设固定收尾仪式：5 分钟复盘",
        "把休息写进计划：续航不是浪费"
      ],
      "tags": [
        "kind:core",
        "tone:warm",
        "topic:energy"
      ],
      "priority": 95,
      "access_level": "preview",
      "module_code": "core_full"
    },
    {
      "id": "growth_core_04",
      "section": "growth",
      "title": "学习策略：要“输入—输出—反馈”闭环",
      "desc": "只有输入不会让你变强。关键是把学习变成可检验的输出与反馈。",
      "bullets": [
        "输入：看/听/学",
        "输出：写/讲/做",
        "反馈：复盘/对比/请教"
      ],
      "tips": [
        "每次学习至少产出 1 个可见成果（卡片/小作品/讲解）",
        "找一个反馈源：同伴/导师/用户/数据"
      ],
      "tags": [
        "kind:core",
        "tone:neutral",
        "topic:learning"
      ],
      "priority": 94,
      "access_level": "preview",
      "module_code": "core_full"
    },
    {
      "id": "growth_core_05",
      "section": "growth",
      "title": "沟通成长：把观点说清楚，比说得多更重要",
      "desc": "成长不仅是能力，也是在关键场景把观点说清楚、推动决策。",
      "bullets": [
        "先结论后理由",
        "用例子替代抽象",
        "把分歧写成选项"
      ],
      "tips": [
        "练习 30 秒表达：结论-依据-下一步",
        "把选择写成 A/B/C，决策会更快"
      ],
      "tags": [
        "kind:core",
        "tone:neutral",
        "topic:communication"
      ],
      "priority": 92,
      "access_level": "preview",
      "module_code": "core_full"
    },
    {
      "id": "growth_core_06",
      "section": "growth",
      "title": "抗压升级：把焦虑变成清单与排序",
      "desc": "压力最大的来源是不确定。把不确定拆成可执行步骤，你会更快稳住。",
      "bullets": [
        "写下担心点",
        "按影响大小排序",
        "先做最高影响的一条"
      ],
      "tips": [
        "只为‘高影响’投入精力，别被小概率耗尽",
        "到线就交付，再迭代"
      ],
      "tags": [
        "kind:core",
        "tone:warm",
        "topic:stress"
      ],
      "priority": 90,
      "access_level": "preview",
      "module_code": "core_full"
    },
    {
      "id": "growth_core_07",
      "section": "growth",
      "title": "长期复利：让你的输出可被看见",
      "desc": "同样的努力，有没有被看见会决定成长速度。把成果可视化，你会更快获得机会。",
      "bullets": [
        "记录成果与指标",
        "沉淀案例与复盘",
        "建立作品集/内容库"
      ],
      "tips": [
        "每月整理一次‘我做成了什么’，形成清单",
        "把最好的 3 个成果放到最显眼的位置"
      ],
      "tags": [
        "kind:core",
        "tone:neutral",
        "topic:visibility"
      ],
      "priority": 88,
      "access_level": "preview",
      "module_code": "core_full"
    }
  ]
}
