{
  "id": "baseline_rc_isfj_a",
  "type": "role_card",
  "title": "温和守护者",
  "slug": "baseline-role-isfj-a",
  "status": "active",
  "type_codes": [
    "ISFJ-A"
  ],
  "points": [
    "关注他人的需要与细节，愿意用稳定支持建立安全感。",
    "执行踏实，擅长把承诺落到具体行动上。",
    "在人际中偏向体贴，但可能忽略自身需求。",
    "面对冲突时倾向回避，需要更清晰的表达。"
  ],
  "actions": [
    "在帮助他人前先确认自身资源，避免透支。",
    "用具体需求替代含糊暗示，让沟通更明确。",
    "为关系设定小范围的共同规则，减少误会。"
  ],
  "disclaimer": "本内容为倾向性参考，不构成诊断或专业建议。",
  "sections": {
    "points": [
      "关注他人的需要与细节，愿意用稳定支持建立安全感。",
      "执行踏实，擅长把承诺落到具体行动上。",
      "在人际中偏向体贴，但可能忽略自身需求。",
      "面对冲突时倾向回避，需要更清晰的表达。"
    ],
    "actions": [
      "在帮助他人前先确认自身资源，避免透支。",
      "用具体需求替代含糊暗示，让沟通更明确。",
      "为关系设定小范围的共同规则，减少误会。"
    ],
    "disclaimer": "本内容为倾向性参考，不构成诊断或专业建议。"
  },
  "body": "你更关注他人的需要与细节，愿意用稳定支持来建立安全感。当别人焦虑或不安时，你会先做能做的事，帮对方把生活重新拉回秩序。你执行踏实，擅长把承诺落到具体行动上，这让人感到可靠与安心。但在关系中，你可能把体贴放在首位而忽略自己的需求，久而久之会累积委屈。面对冲突时，你倾向回避或缓和，担心直接表达会破坏关系。实际上，清晰表达需求反而能减少误会，让关系更稳固。在帮助他人之前先确认自身资源，是对双方都负责任的选择。用具体请求替代含糊暗示，会让对方更容易理解并给出回应。为关系设定小范围的共同规则，如沟通时间或分工方式，能降低不必要的摩擦。当你把照顾他人与照顾自己放在同一张清单上，你的温和会更有力量。当你感到不舒服时，用“我需要……”开头表达，会比解释原因更容易被接住。你也可以给自己设定可拒绝的清单，提醒自己帮助是选择而不是义务。把自己的休息安排提前写入日程，会让支持他人更可持续。如果对方持续忽略你的界限，可以用更具体的行动规则来保护自己，例如明确“我可以帮助到几点”。把“我能做到的”与“我愿意做到的”区分开，会减少内心冲突。在团队协作中，学会把任务转交给合适的人，避免过度承担。当你被需要时也保留选择权，会更自在。把感受说清楚，关系会更稳。"
}
